Metadata-Version: 2.4
Name: pbdm
Version: 0.0.3
Summary: CASAS PBDM Python implementation
Author-email: George Simmons <g.simmons@idems.international>, Luigi Ponti <quartese@gmail.com>, Chiara Facciolà <chiara.facciola@idems.international>, David Stern <d.stern@idems.international>
Classifier: Programming Language :: Python :: 3
Requires-Python: >=3.10
License-File: LICENSE
License-File: COPYING
License-File: AUTHORS
Requires-Dist: psymple>=0.3.4
Dynamic: license-file
